nodelist_inflator/__init__.py
nodelist_inflator/nodelist_infate.py
nodelist_inflator-0.2.0.dist-info/METADATA
nodelist_inflator-0.2.0.dist-info/WHEEL
nodelist_inflator-0.2.0.dist-info/entry_points.txt
nodelist_inflator-0.2.0.dist-info/top_level.txt
nodelist_inflator-0.2.0.dist-info/RECORD
