Metadata-Version: 2.1
Name: nodelist-inflator
Version: 0.2.0
Summary: Expands hostnames/nodelists
Home-page: https://github.com/zanussbaum/nodelist-inflator
Author: Zach Nussbaum
Author-email: zanussbaum@gmail.com
License: MIT license
Keywords: nodelist_inflator,slurm,hostnames
Classifier: Development Status :: 2 - Pre-Alpha
Classifier: Intended Audience :: Developers
Classifier: License :: OSI Approved :: MIT License
Classifier: Natural Language :: English
Classifier: Programming Language :: Python :: 3
Classifier: Programming Language :: Python :: 3.6
Classifier: Programming Language :: Python :: 3.7
Classifier: Programming Language :: Python :: 3.8
Requires-Python: >=3.6
